dextbird-0.4.9.dist-info/METADATA
dextbird-0.4.9.dist-info/WHEEL
dextbird-0.4.9.dist-info/license_files/LICENSE
dextbird/__init__.py
dextbird/plug.py
dextbird/voice_client.py
dextbird/core.pyi
dextbird/dextbird.cpython-38-x86_64-linux-gnu.so
dextbird-0.4.9.dist-info/RECORD
