Metadata-Version: 2.3
Name: dextbird
Version: 0.4.9
Classifier: Programming Language :: Rust
Classifier: Programming Language :: Python :: Implementation :: CPython
Classifier: Programming Language :: Python :: Implementation :: PyPy
License-File: LICENSE
Summary: Discord extensions voice library made with rust
Requires-Python: >=3.8
